opensearch_requests/__init__.py
opensearch_requests/search/__init__.py
opensearch_requests/search/aggregations/__init__.py
opensearch_requests/search/aggregations/base.py
opensearch_requests/search/aggregations/bucket.py
opensearch_requests/search/aggregations/metric.py
opensearch_requests/search/aggregations/options.py
opensearch_requests/search/queries/__init__.py
opensearch_requests/search/queries/base.py
opensearch_requests/search/queries/boolean.py
opensearch_requests/search/queries/enums.py
opensearch_requests/search/queries/full_text.py
opensearch_requests/search/queries/match_all.py
opensearch_requests/search/queries/options.py
opensearch_requests/search/queries/term.py
opensearch_requests/search/result/__init__.py
opensearch_requests-0.0.12.dist-info/LICENSE
opensearch_requests-0.0.12.dist-info/METADATA
opensearch_requests-0.0.12.dist-info/WHEEL
opensearch_requests-0.0.12.dist-info/RECORD
